cal_poetry/__init__.py
cal_poetry/app.py
cal_poetry-0.1.0.dist-info/WHEEL
cal_poetry-0.1.0.dist-info/METADATA
cal_poetry-0.1.0.dist-info/RECORD
