Metadata-Version: 2.1
Name: cal-poetry
Version: 0.1.0
Summary: 
Author: Krushna Panchvishe
Author-email: krushna.4997@gmail.com
Requires-Python: >=3.9,<4.0
Classifier: Programming Language :: Python :: 3
Classifier: Programming Language :: Python :: 3.10
Classifier: Programming Language :: Python :: 3.9
Requires-Dist: numpy (>=1.23.1,<2.0.0)
